dns_sprockets.py
dns_sprockets_version.py
dns_sprockets_lib/__init__.py
dns_sprockets_lib/dns_sprockets_impl.py
dns_sprockets_lib/dns_utils.py
dns_sprockets_lib/dnssec_nsecx.py
dns_sprockets_lib/loader_classes.py
dns_sprockets_lib/utils.py
dns_sprockets_lib/validator_classes.py
dns_sprockets_lib/loaders/__init__.py
dns_sprockets_lib/loaders/file.py
dns_sprockets_lib/loaders/xfr.py
dns_sprockets_lib/loaders/tests/__init__.py
dns_sprockets_lib/loaders/tests/test___init__.py
dns_sprockets_lib/loaders/tests/test_file.py
dns_sprockets_lib/tests/__init__.py
dns_sprockets_lib/tests/test_dns_sprockets_impl.py
dns_sprockets_lib/tests/test_dns_utils.py
dns_sprockets_lib/tests/test_dnssec_nsecx.py
dns_sprockets_lib/tests/test_loader_classes.py
dns_sprockets_lib/tests/test_utils.py
dns_sprockets_lib/tests/test_validator_classes.py
dns_sprockets_lib/tests/data/001.cst.net.
dns_sprockets_lib/tests/data/001.cst.net._bad_dnskey
dns_sprockets_lib/tests/data/001.cst.net._bad_ns
dns_sprockets_lib/tests/data/001.cst.net._bad_nsec3_ttl
dns_sprockets_lib/tests/data/001.cst.net._bad_nsec3param
dns_sprockets_lib/tests/data/001.cst.net._bad_rrsig_covers
dns_sprockets_lib/tests/data/001.cst.net._bad_rrsig_signer
dns_sprockets_lib/tests/data/001.cst.net._bad_rrsig_time
dns_sprockets_lib/tests/data/001.cst.net._bad_rrsig_ttls
dns_sprockets_lib/tests/data/001.cst.net._bad_soa
dns_sprockets_lib/tests/data/001.cst.net._extra_nsec
dns_sprockets_lib/tests/data/001.cst.net._mult_soa
dns_sprockets_lib/tests/data/001.cst.net._no_soa
dns_sprockets_lib/tests/data/001.cst.net._only_nsec
dns_sprockets_lib/tests/data/001.cst.net._rrsig_bad_algo
dns_sprockets_lib/tests/data/001.cst.net._rrsig_missing
dns_sprockets_lib/tests/data/001.cst.net._rrsig_orphan
dns_sprockets_lib/tests/data/001.cst.net._zsk_not_origin
dns_sprockets_lib/tests/data/rfc4035_example.
dns_sprockets_lib/tests/data/rfc4035_example._bad_nsec_covers
dns_sprockets_lib/tests/data/rfc4035_example._chain_broke
dns_sprockets-2.0.0.dist-info/AUTHORS.txt
dns_sprockets-2.0.0.dist-info/LICENSE.txt
dns_sprockets-2.0.0.dist-info/METADATA
dns_sprockets-2.0.0.dist-info/WHEEL
dns_sprockets-2.0.0.dist-info/entry_points.txt
dns_sprockets-2.0.0.dist-info/top_level.txt
dns_sprockets-2.0.0.dist-info/RECORD
