Metadata-Version: 2.1
Name: dns-sprockets
Version: 2.0.0
Summary: Command-line DNS Zone validation tool
Home-page: https://github.com/ultradns/dns_sprockets
Author: Ashley Roeckelein
Author-email: ashley.roeckelein@neustar.biz
Maintainer: Ashley Roeckelein
Maintainer-email: ashley.roeckelein@neustar.biz
License: Apache License, Version 2.0
Keywords: DNS zone validation
Platform: UNKNOWN
Classifier: Development Status :: 5 - Production/Stable
Classifier: Environment :: Console
Classifier: Intended Audience :: Customer Service
Classifier: Intended Audience :: Developers
Classifier: Intended Audience :: Information Technology
Classifier: Intended Audience :: System Administrators
Classifier: Intended Audience :: Telecommunications Industry
Classifier: License :: OSI Approved :: Apache Software License
Classifier: Natural Language :: English
Classifier: Operating System :: OS Independent
Classifier: Programming Language :: Python :: 3 :: Only
Classifier: Programming Language :: Python :: 3.8
Classifier: Topic :: Internet :: Name Service (DNS)
Classifier: Topic :: Software Development :: Quality Assurance
Classifier: Topic :: Software Development :: Testing
Classifier: Topic :: System :: Networking :: Monitoring
Classifier: Topic :: System :: Systems Administration
Classifier: Topic :: Utilities
Requires-Dist: dnspython (>=1.16.0)
Requires-Dist: pycryptodome (>=3.9.7)
